csj.py
csj-2019.2.16.dist-info/LICENSE
csj-2019.2.16.dist-info/METADATA
csj-2019.2.16.dist-info/WHEEL
csj-2019.2.16.dist-info/top_level.txt
csj-2019.2.16.dist-info/RECORD
